{
  "fetch_time": "2024-12-11 09:21:24",
  "exchange_rates_time": "2024-12-11 01:21:25",
  "countries": {
    "巴哈马 (美元)": {
      "50GB": "¥7.17",
      "200GB": "¥21.67",
      "2TB": "¥79.64",
      "6TB": "¥239.06",
      "12TB": "¥470.94"
    },
    "巴巴多斯 (美元)": {
      "50GB": "¥7.17",
      "200GB": "¥25.29",
      "2TB": "¥86.88",
      "6TB": "¥253.55",
      "12TB": "¥507.17"
    },
    "巴西 (巴西雷亚尔)": {
      "50GB": "¥5.87",
      "200GB": "¥17.84",
      "2TB": "¥59.76",
      "6TB": "¥179.52",
      "12TB": "¥359.16"
    },
    "加拿大 (加元)": {
      "50GB": "¥6.62",
      "200GB": "¥20.46",
      "2TB": "¥66.62",
      "6TB": "¥205.08",
      "12TB": "¥410.21"
    },
    "智利 (智利比索)": {
      "50GB": "¥5.91",
      "200GB": "¥18.63",
      "2TB": "¥63.54",
      "6TB": "¥224.44",
      "12TB": "¥448.96"
    },
    "哥伦比亚 (哥伦比亚比索)": {
      "50GB": "¥6.42",
      "200GB": "¥21.24",
      "2TB": "¥73.94",
      "6TB": "¥213.91",
      "12TB": "¥444.46"
    },
    "墨西哥 (墨西哥比索)": {
      "50GB": "¥6.12",
      "200GB": "¥17.63",
      "2TB": "¥64.39",
      "6TB": "¥179.5",
      "12TB": "¥359.35"
    },
    "秘鲁 (秘鲁索尔)": {
      "50GB": "¥5.65",
      "200GB": "¥19.3",
      "2TB": "¥68.03",
      "6TB": "¥194.74",
      "12TB": "¥389.67"
    },
    "苏里南 (美元)": {
      "50GB": "¥7.17",
      "200GB": "¥25.29",
      "2TB": "¥86.88",
      "6TB": "¥253.55",
      "12TB": "¥507.17"
    },
    "美国 (美元)": {
      "50GB": "¥7.17",
      "200GB": "¥21.67",
      "2TB": "¥72.39",
      "6TB": "¥217.32",
      "12TB": "¥434.71"
    },
    "阿尔巴尼亚 (美元)": {
      "50GB": "¥8.62",
      "200GB": "¥25.29",
      "2TB": "¥86.88",
      "6TB": "¥253.55",
      "12TB": "¥507.17"
    },
    "巴林 (美元)": {
      "50GB": "¥7.17",
      "200GB": "¥21.67",
      "2TB": "¥79.64",
      "6TB": "¥239.06",
      "12TB": "¥470.94"
    },
    "白俄罗斯 (美元)": {
      "50GB": "¥8.62",
      "200GB": "¥25.29",
      "2TB": "¥86.88",
      "6TB": "¥253.55",
      "12TB": "¥507.17"
    },
    "贝宁 (美元)": {
      "50GB": "¥7.17",
      "200GB": "¥25.29",
      "2TB": "¥86.88",
      "6TB": "¥253.55",
      "12TB": "¥507.17"
    },
    "保加利亚 (保加利亚列弗)": {
      "50GB": "¥7.77",
      "200GB": "¥23.4",
      "2TB": "¥81.99",
      "6TB": "¥253.87",
      "12TB": "¥507.77"
    },
    "喀麦隆 (美元)": {
      "50GB": "¥7.17",
      "200GB": "¥25.29",
      "2TB": "¥86.88",
      "6TB": "¥253.55",
      "12TB": "¥507.17"
    },
    "克罗地亚 (欧元)": {
      "50GB": "¥7.56",
      "200GB": "¥22.82",
      "2TB": "¥76.26",
      "6TB": "¥228.93",
      "12TB": "¥457.94"
    },
    "捷克 (捷克克朗)": {
      "50GB": "¥7.62",
      "200GB": "¥24.09",
      "2TB": "¥75.91",
      "6TB": "¥228.35",
      "12TB": "¥454.27"
    },
    "丹麦 (丹麦克朗)": {
      "50GB": "¥9.22",
      "200GB": "¥25.61",
      "2TB": "¥91.19",
      "6TB": "¥275.61",
      "12TB": "¥562.5"
    },
    "埃及 (埃及镑)": {
      "50GB": "¥5.75",
      "200GB": "¥21.58",
      "2TB": "¥71.94",
      "6TB": "¥215.83",
      "12TB": "¥431.65"
    },
    "欧盟 (欧元)": {
      "50GB": "¥7.56",
      "200GB": "¥22.82",
      "2TB": "¥76.26",
      "6TB": "¥228.93",
      "12TB": "¥457.94"
    },
    "格鲁吉亚 (美元)": {
      "50GB": "¥7.17",
      "200GB": "¥25.29",
      "2TB": "¥86.88",
      "6TB": "¥253.55",
      "12TB": "¥507.17"
    },
    "加纳 (美元)": {
      "50GB": "¥7.17",
      "200GB": "¥25.29",
      "2TB": "¥86.88",
      "6TB": "¥253.55",
      "12TB": "¥507.17"
    },
    "匈牙利 (匈牙利福林)": {
      "50GB": "¥7.43",
      "200GB": "¥24.01",
      "2TB": "¥83.58",
      "6TB": "¥241.81",
      "12TB": "¥502.42"
    },
    "冰岛 (美元)": {
      "50GB": "¥8.62",
      "200GB": "¥26.74",
      "2TB": "¥86.88",
      "6TB": "¥253.55",
      "12TB": "¥507.17"
    },
    "以色列 (以色列新谢克尔)": {
      "50GB": "¥7.91",
      "200GB": "¥24.14",
      "2TB": "¥80.93",
      "6TB": "¥243.2",
      "12TB": "¥486.61"
    },
    "科特迪瓦 (美元)": {
      "50GB": "¥7.17",
      "200GB": "¥25.29",
      "2TB": "¥86.88",
      "6TB": "¥253.55",
      "12TB": "¥507.17"
    },
    "肯尼亚 (美元)": {
      "50GB": "¥7.17",
      "200GB": "¥25.29",
      "2TB": "¥86.88",
      "6TB": "¥253.55",
      "12TB": "¥507.17"
    },
    "摩尔多瓦 (美元)": {
      "50GB": "¥7.17",
      "200GB": "¥25.29",
      "2TB": "¥86.88",
      "6TB": "¥253.55",
      "12TB": "¥507.17"
    },
    "尼日利亚 (尼日利亚奈拉)": {
      "50GB": "¥4.23",
      "200GB": "¥13.63",
      "2TB": "¥46.55",
      "6TB": "¥126.48",
      "12TB": "¥211.11"
    },
    "挪威 (挪威克朗)": {
      "50GB": "¥7.79",
      "200GB": "¥25.32",
      "2TB": "¥83.77",
      "6TB": "¥259.09",
      "12TB": "¥518.83"
    },
    "巴基斯坦 (巴基斯坦卢比)": {
      "50GB": "¥5.22",
      "200GB": "¥20.89",
      "2TB": "¥65.29",
      "6TB": "¥232.44",
      "12TB": "¥467.48"
    },
    "波兰 (波兰兹罗提)": {
      "50GB": "¥8.94",
      "200GB": "¥26.86",
      "2TB": "¥89.59",
      "6TB": "¥268.8",
      "12TB": "¥537.62"
    },
    "卡塔尔 (卡塔尔里亚尔)": {
      "50GB": "¥7.35",
      "200GB": "¥21.89",
      "2TB": "¥73.69",
      "6TB": "¥219.1",
      "12TB": "¥438.23"
    },
    "罗马尼亚 (罗马尼亚列伊)": {
      "50GB": "¥7.67",
      "200GB": "¥23.03",
      "2TB": "¥76.79",
      "6TB": "¥230.4",
      "12TB": "¥460.81"
    },
    "俄罗斯 (俄罗斯卢布)": {
      "50GB": "¥4.19",
      "200GB": "¥10.58",
      "2TB": "¥42.54",
      "6TB": "¥247.87",
      "12TB": "¥496.45"
    },
    "沙特阿拉伯 (沙特里亚尔)": {
      "50GB": "¥7.72",
      "200GB": "¥25.13",
      "2TB": "¥87.02",
      "6TB": "¥251.43",
      "12TB": "¥522.22"
    },
    "塞内加尔 (美元)": {
      "50GB": "¥7.17",
      "200GB": "¥25.29",
      "2TB": "¥86.88",
      "6TB": "¥253.55",
      "12TB": "¥507.17"
    },
    "南非 (南非兰特)": {
      "50GB": "¥6.09",
      "200GB": "¥24.39",
      "2TB": "¥81.3",
      "6TB": "¥243.9",
      "12TB": "¥487.8"
    },
    "瑞典 (瑞典克朗)": {
      "50GB": "¥7.95",
      "200GB": "¥25.83",
      "2TB": "¥85.43",
      "6TB": "¥264.24",
      "12TB": "¥529.14"
    },
    "瑞士 (瑞士法郎)": {
      "50GB": "¥8.26",
      "200GB": "¥24.79",
      "2TB": "¥82.64",
      "6TB": "¥247.93",
      "12TB": "¥495.87"
    },
    "坦桑尼亚 (坦桑尼亚先令)": {
      "50GB": "¥7.22",
      "200GB": "¥25.69",
      "2TB": "¥86.32",
      "6TB": "¥259.54",
      "12TB": "¥519.37"
    },
    "土耳其 (新土耳其里拉)": {},
    "乌干达 (美元)": {
      "50GB": "¥7.17",
      "200GB": "¥25.29",
      "2TB": "¥86.88",
      "6TB": "¥253.55",
      "12TB": "¥507.17"
    },
    "阿拉伯联合酋长国 (阿联酋迪拉姆)": {
      "50GB": "¥7.89",
      "200GB": "¥23.7",
      "2TB": "¥79.03",
      "6TB": "¥237.13",
      "12TB": "¥474.29"
    },
    "英国 (英镑)": {
      "50GB": "¥9.17",
      "200GB": "¥27.69",
      "2TB": "¥83.24",
      "6TB": "¥249.91",
      "12TB": "¥509.17"
    },
    "赞比亚 (美元)": {
      "50GB": "¥7.17",
      "200GB": "¥25.29",
      "2TB": "¥86.88",
      "6TB": "¥253.55",
      "12TB": "¥507.17"
    },
    "津巴布韦 (美元)": {
      "50GB": "¥7.17",
      "200GB": "¥25.29",
      "2TB": "¥86.88",
      "6TB": "¥253.55",
      "12TB": "¥507.17"
    },
    "澳大利亚 (澳元)": {
      "50GB": "¥6.9",
      "200GB": "¥20.79",
      "2TB": "¥69.4",
      "6TB": "¥208.29",
      "12TB": "¥416.62"
    },
    "柬埔寨 (美元)": {
      "50GB": "¥7.17",
      "200GB": "¥21.67",
      "2TB": "¥79.64",
      "6TB": "¥239.06",
      "12TB": "¥470.94"
    },
    "中国大陆 (人民币)": {
      "50GB": "¥6.0",
      "200GB": "¥21.0",
      "2TB": "¥68.0",
      "6TB": "¥198.0",
      "12TB": "¥398.0"
    },
    "香港 (港元)": {
      "50GB": "¥7.48",
      "200GB": "¥21.5",
      "2TB": "¥72.9",
      "6TB": "¥222.43",
      "12TB": "¥437.38"
    },
    "印度 (印度卢比)": {
      "50GB": "¥6.41",
      "200GB": "¥18.72",
      "2TB": "¥64.02",
      "6TB": "¥256.32",
      "12TB": "¥504.27"
    },
    "印度尼西亚 (印尼卢比)": {
      "50GB": "¥6.85",
      "200GB": "¥22.38",
      "2TB": "¥77.19",
      "6TB": "¥227.9",
      "12TB": "¥456.27"
    },
    "日本 (日元)": {
      "50GB": "¥7.17",
      "200GB": "¥21.52",
      "2TB": "¥71.74",
      "6TB": "¥215.21",
      "12TB": "¥430.42"
    },
    "哈萨克斯坦 (哈萨克斯坦坚戈)": {
      "50GB": "¥7.09",
      "200GB": "¥21.17",
      "2TB": "¥70.9",
      "6TB": "¥212.99",
      "12TB": "¥426.12"
    },
    "吉尔吉斯斯坦 (美元)": {
      "50GB": "¥7.17",
      "200GB": "¥21.67",
      "2TB": "¥79.64",
      "6TB": "¥239.06",
      "12TB": "¥470.94"
    },
    "马来西亚 (马来西亚林吉特)": {
      "50GB": "¥6.39",
      "200GB": "¥19.51",
      "2TB": "¥73.61",
      "6TB": "¥212.95",
      "12TB": "¥442.46"
    },
    "尼泊尔 (美元)": {
      "50GB": "¥7.17",
      "200GB": "¥25.29",
      "2TB": "¥86.88",
      "6TB": "¥253.55",
      "12TB": "¥507.17"
    },
    "新西兰 (新西兰元)": {
      "50GB": "¥7.13",
      "200GB": "¥21.05",
      "2TB": "¥71.69",
      "6TB": "¥210.93",
      "12TB": "¥421.9"
    },
    "菲律宾 (菲律宾比索)": {
      "50GB": "¥6.12",
      "200GB": "¥22.38",
      "2TB": "¥74.88",
      "6TB": "¥223.75",
      "12TB": "¥448.75"
    },
    "韩国 (韩元)": {
      "50GB": "¥5.57",
      "200GB": "¥22.29",
      "2TB": "¥70.93",
      "6TB": "¥222.92",
      "12TB": "¥445.84"
    },
    "新加坡 (新加坡元)": {
      "50GB": "¥8.0",
      "200GB": "¥21.51",
      "2TB": "¥75.57",
      "6TB": "¥232.32",
      "12TB": "¥459.35"
    },
    "台湾 (新台币)": {
      "50GB": "¥6.7",
      "200GB": "¥20.09",
      "2TB": "¥66.96",
      "6TB": "¥200.89",
      "12TB": "¥399.55"
    },
    "塔吉克斯坦 (美元)": {
      "50GB": "¥7.17",
      "200GB": "¥21.67",
      "2TB": "¥79.64",
      "6TB": "¥239.06",
      "12TB": "¥470.94"
    },
    "泰国 (泰铢)": {
      "50GB": "¥7.53",
      "200GB": "¥21.29",
      "2TB": "¥85.81",
      "6TB": "¥255.91",
      "12TB": "¥513.98"
    },
    "乌兹别克斯坦 (美元)": {
      "50GB": "¥7.17",
      "200GB": "¥21.67",
      "2TB": "¥79.64",
      "6TB": "¥239.06",
      "12TB": "¥470.94"
    },
    "越南 (越南盾)": {
      "50GB": "¥5.44",
      "200GB": "¥19.74",
      "2TB": "¥71.23",
      "6TB": "¥214.26",
      "12TB": "¥428.81"
    }
  }
}